django_sample_components/__init__.py
django_sample_components/admin.py
django_sample_components/apps.py
django_sample_components/models.py
django_sample_components/static/css/components/typewriter.css
django_sample_components/static/css/style.css
django_sample_components/static/js/components/typewriter.js
django_sample_components/static/js/main.js
django_sample_components/templates/django_sample_components/components/simple_alert.html
django_sample_components/templates/django_sample_components/components/simple_typewriter.html
django_sample_components/templates/django_sample_components/pages/alert.html
django_sample_components/templates/django_sample_components/pages/greeting.html
django_sample_components/templates/django_sample_components/pages/home.html
django_sample_components/templates/django_sample_components/pages/master.html
django_sample_components/templates/django_sample_components/pages/typewriter.html
django_sample_components/templates/django_sample_components/partials/menu.html
django_sample_components/templatetags/__init__.py
django_sample_components/templatetags/sample_tags/__init__.py
django_sample_components/templatetags/sample_tags/greeting.py
django_sample_components/templatetags/sample_tags/shout.py
django_sample_components/templatetags/sample_tags/show_today_timestamp.py
django_sample_components/templatetags/sample_tags/simple_alert.py
django_sample_components/templatetags/sample_tags/simple_typewriter.py
django_sample_components/urls.py
django_sample_components/views.py
django_sample_components-0.1.2.dist-info/METADATA
django_sample_components-0.1.2.dist-info/WHEEL
django_sample_components-0.1.2.dist-info/licenses/LICENSE
django_sample_components-0.1.2.dist-info/RECORD
